<?xml version="1.0" encoding="utf-8"?>
<LinearLayout xmlns:android="http://schemas.android.com/apk/res/android"
    xmlns:app="http://schemas.android.com/apk/res-auto"
    xmlns:tools="http://schemas.android.com/tools"
    android:layout_width="match_parent"
    android:layout_height="match_parent"
    tools:context=".MainActivity"
    android:orientation="vertical"
    android:weightSum="10">

    <RelativeLayout
        android:layout_width="match_parent"
        android:layout_height="0dp"
        android:layout_weight="8">

        <ImageView
            android:layout_width="match_parent"
            android:layout_height="match_parent"
            android:scaleType="fitXY"
            android:src="@drawable/poker_table">

        </ImageView>

        <TextView
            android:layout_width="wrap_content"
            android:layout_height="wrap_content"
            android:layout_marginLeft="300dp"
            android:layout_marginTop="85dp"
            android:background="#EAF0F1"
            android:text="POT">

        </TextView>

        <TextView
            android:layout_width="wrap_content"
            android:layout_height="wrap_content"
            android:layout_marginLeft="260dp"
            android:layout_marginTop="300dp"
            android:background="#FBE685"
            android:text="STACK :">

        </TextView>

        <TextView
            android:layout_width="wrap_content"
            android:layout_height="wrap_content"
            android:layout_marginLeft="320dp"
            android:layout_marginTop="300dp"
            android:background="#FBE685"
            android:text="10000">

        </TextView>

        <TextView
            android:layout_width="wrap_content"
            android:layout_height="wrap_content"
            android:layout_marginLeft="340dp"
            android:layout_marginTop="85dp"
            android:background="#EAF0F1"
            android:text="20000">

        </TextView>

        <TextView
            android:layout_width="wrap_content"
            android:layout_height="wrap_content"
            android:layout_marginLeft="5dp"
            android:layout_marginTop="5dp"
            android:background="#EAF0F1"
            android:text="COMBINATION RESULT">

        </TextView>

        <LinearLayout
            android:layout_width="wrap_content"
            android:layout_height="wrap_content"
            android:layout_marginLeft="240dp"
            android:layout_marginTop="120dp"
            android:weightSum="5">

            <ImageView
                android:layout_width="wrap_content"
                android:layout_height="wrap_content"
                android:layout_weight="1"
                android:background="@drawable/back">

            </ImageView>

            <ImageView
                android:layout_width="wrap_content"
                android:layout_height="wrap_content"
                android:layout_weight="1"
                android:background="@drawable/back">

            </ImageView>

            <ImageView
                android:layout_width="wrap_content"
                android:layout_height="wrap_content"
                android:layout_weight="1"
                android:background="@drawable/back">

            </ImageView>

            <ImageView
                android:layout_width="wrap_content"
                android:layout_height="wrap_content"
                android:layout_weight="1"
                android:background="@drawable/back">

            </ImageView>

            <ImageView
                android:layout_width="wrap_content"
                android:layout_height="wrap_content"
                android:layout_weight="1"
                android:background="@drawable/back">

            </ImageView>


        </LinearLayout>


        <LinearLayout
            android:layout_width="wrap_content"
            android:layout_height="wrap_content"
            android:layout_marginLeft="320dp"
            android:layout_marginTop="235dp"
            android:weightSum="5">

            <ImageView
                android:layout_width="wrap_content"
                android:layout_height="wrap_content"
                android:layout_weight="1"
                android:background="@drawable/back">

            </ImageView>

            <ImageView
                android:layout_width="wrap_content"
                android:layout_height="wrap_content"
                android:layout_weight="1"
                android:background="@drawable/back">

            </ImageView>
        </LinearLayout>


    </RelativeLayout>


    <LinearLayout
        android:layout_width="match_parent"
        android:layout_height="0dp"
        android:layout_weight="2"
        android:orientation="horizontal"
        android:weightSum="12">

        <Button
            android:layout_width="0dp"
            android:layout_height="match_parent"
            android:layout_weight="2"
            android:text="NEW GAME">

        </Button>

        <Button
            android:layout_width="0dp"
            android:layout_height="match_parent"
            android:layout_weight="2"
            android:text="DEAL NEXT">

        </Button>

        <Button
            android:layout_width="0dp"
            android:layout_height="match_parent"
            android:layout_weight="2"
            android:text="FOLD">

        </Button>

        <Button
            android:layout_width="0dp"
            android:layout_height="match_parent"
            android:layout_weight="2"
            android:text="CHECK">

        </Button>

        <Button
            android:layout_width="0dp"
            android:layout_height="match_parent"
            android:layout_weight="2"
            android:text="CALL">

        </Button>

        <Button
            android:layout_width="0dp"
            android:layout_height="match_parent"
            android:layout_weight="2"
            android:text="RAISE">

        </Button>

    </LinearLayout>


</LinearLayout>